clipstitcher/__init__.py
clipstitcher/client_sync.py
clipstitcher/scene_objects.py
clipstitcher/styles.css
clipstitcher-0.2.5.dist-info/licenses/LICENSE
clipstitcher-0.2.5.dist-info/METADATA
clipstitcher-0.2.5.dist-info/WHEEL
clipstitcher-0.2.5.dist-info/top_level.txt
clipstitcher-0.2.5.dist-info/RECORD
