Metadata-Version: 2.4
Name: clipstitcher
Version: 0.2.5
Summary: A python package for quick cutting video sequences
Home-page: https://github.com/LiborKudela/clipsticher
Author: Libor Kudela
Author-email: libor.kudela1@gmail.com
Keywords: video,editing,sequence,rendering
Classifier: Natural Language :: English
Classifier: Development Status :: 2 - Pre-Alpha
Classifier: Programming Language :: Python :: 3.8
Classifier: Operating System :: POSIX :: Linux
Requires-Python: >3.8.0
License-File: LICENSE
Requires-Dist: numpy>=1.20.2
Requires-Dist: opencv-python>=4.6.0.66
Requires-Dist: requests>=2.28.1
Requires-Dist: selenium>=4.6.0
Requires-Dist: tqdm>=4.64.1
Requires-Dist: python-vlc>=3.0.20123
Requires-Dist: tqdm>=4.66.1
Requires-Dist: paramiko>=3.2.0
Dynamic: author
Dynamic: author-email
Dynamic: classifier
Dynamic: description
Dynamic: description-content-type
Dynamic: home-page
Dynamic: keywords
Dynamic: license-file
Dynamic: requires-dist
Dynamic: requires-python
Dynamic: summary
